pyhercules.py
pyhercules_app.py
pyhercules_functions.py
pyhercules-1.0.2.dist-info/licenses/LICENSE
pyhercules-1.0.2.dist-info/METADATA
pyhercules-1.0.2.dist-info/WHEEL
pyhercules-1.0.2.dist-info/entry_points.txt
pyhercules-1.0.2.dist-info/top_level.txt
pyhercules-1.0.2.dist-info/RECORD
