Metadata-Version: 2.4
Name: pyhercules
Version: 1.0.2
Summary: A flexible framework for hierarchical clustering of text, numeric, or image data using LLMs.
Home-page: https://github.com/bandeerun/pyhercules
Author: Bandee
Author-email: bandeerun@gmail.com
Classifier: Programming Language :: Python :: 3
Classifier: Programming Language :: Python :: 3.9
Classifier: Programming Language :: Python :: 3.10
Classifier: Programming Language :: Python :: 3.11
Classifier: License :: OSI Approved :: MIT License
Classifier: Operating System :: OS Independent
Classifier: Intended Audience :: Science/Research
Classifier: Intended Audience :: Developers
Classifier: Topic :: Scientific/Engineering :: Artificial Intelligence
Classifier: Topic :: Software Development :: Libraries :: Python Modules
Requires-Python: >=3.9
License-File: LICENSE
Requires-Dist: numpy
Requires-Dist: pandas
Requires-Dist: scikit-learn
Requires-Dist: Pillow
Provides-Extra: models
Requires-Dist: accelerate; extra == "models"
Requires-Dist: google-generativeai; extra == "models"
Requires-Dist: huggingface_hub; extra == "models"
Requires-Dist: sentence-transformers; extra == "models"
Requires-Dist: torch; extra == "models"
Requires-Dist: transformers; extra == "models"
Requires-Dist: requests; extra == "models"
Requires-Dist: python-dotenv; extra == "models"
Provides-Extra: app
Requires-Dist: accelerate; extra == "app"
Requires-Dist: google-generativeai; extra == "app"
Requires-Dist: huggingface_hub; extra == "app"
Requires-Dist: sentence-transformers; extra == "app"
Requires-Dist: torch; extra == "app"
Requires-Dist: transformers; extra == "app"
Requires-Dist: requests; extra == "app"
Requires-Dist: python-dotenv; extra == "app"
Requires-Dist: dash; extra == "app"
Requires-Dist: dash-bootstrap-components; extra == "app"
Requires-Dist: plotly; extra == "app"
Dynamic: author
Dynamic: author-email
Dynamic: classifier
Dynamic: description
Dynamic: description-content-type
Dynamic: home-page
Dynamic: license-file
Dynamic: provides-extra
Dynamic: requires-dist
Dynamic: requires-python
Dynamic: summary
